certauth/__init__.py
certauth/certauth.py
certauth-1.3.0.dist-info/DESCRIPTION.rst
certauth-1.3.0.dist-info/METADATA
certauth-1.3.0.dist-info/RECORD
certauth-1.3.0.dist-info/WHEEL
certauth-1.3.0.dist-info/entry_points.txt
certauth-1.3.0.dist-info/metadata.json
certauth-1.3.0.dist-info/top_level.txt
certauth-1.3.0.dist-info/zip-safe
